README.rst
setup.py
src/starpa/__init__.py
src/starpa/__main__.py
src/starpa/align.py
src/starpa/annotation.py
src/starpa/cluster.py
src/starpa/docopt.py
src/starpa/identify.py
src/starpa/pseudoSE.py
src/starpa/quantify.py
src/starpa/sort.py
src/starpa/trim.py
src/starpa.egg-info/PKG-INFO
src/starpa.egg-info/SOURCES.txt
src/starpa.egg-info/dependency_links.txt
src/starpa.egg-info/entry_points.txt
src/starpa.egg-info/requires.txt
src/starpa.egg-info/top_level.txt
src/starpa/data/config.txt
src/starpa/data/libraries.txt