Metadata-Version: 1.1
Name: starpa
Version: 0.2.1
Summary: Stable RNA processing product analyzer
Home-page: https://github.com/luidale/starpa
Author: Hannes Luidalepp
Author-email: luidale@gmail.com
License: The GNU General Public License v3.0 (GPL3) - http://www.gnu.org/copyleft/gpl.html
Download-URL: https://github.com/luidale/starpa/archive/v0.2.1.tar.gz
Platform: UNKNOWN
Classifier: Development Status :: 2 - Pre-Alpha
Classifier: Programming Language :: Python :: 3
Classifier: Programming Language :: Python :: 3.4
Classifier: Programming Language :: Python :: 3.5
Classifier: Programming Language :: Python :: 3.6
Classifier: Environment :: Console
Classifier: Intended Audience :: Science/Research
Classifier: License :: OSI Approved :: GNU General Public License v3 (GPLv3)
Classifier: Operating System :: Unix
Classifier: Topic :: Scientific/Engineering
Classifier: Topic :: Scientific/Engineering :: Bio-Informatics
